evalidate/__init__.py
evalidate/credits.txt
evalidate/security.py
evalidate/cli/genfakeproducts.py
evalidate/cli/jg.py
evalidate-2.1.3.dist-info/METADATA
evalidate-2.1.3.dist-info/WHEEL
evalidate-2.1.3.dist-info/entry_points.txt
evalidate-2.1.3.dist-info/licenses/LICENSE
evalidate-2.1.3.dist-info/RECORD
