Metadata-Version: 2.4
Name: evalidate
Version: 2.1.3
Summary: Validation and secure evaluation of untrusted python expressions
Project-URL: Homepage, https://github.com/yaroslaff/evalidate
Project-URL: Issues, https://github.com/yaroslaff/evalidate/issues
Author-email: Yaroslav Polyakov <yaroslaff@gmail.com>
License-File: LICENSE
Keywords: eval,evaluate,evaluation,expression,filter,grep,jg,jq,json,python,safe,sandbox,secure,security,validate
Classifier: License :: OSI Approved :: MIT License
Classifier: Operating System :: OS Independent
Classifier: Programming Language :: Python :: 3
Requires-Python: >=3.8
Provides-Extra: generate
Requires-Dist: faker; extra == 'generate'
